{
  "dependencies": {
    "mssql1": {
      "resourceId": "/subscriptions/[parameters('subscriptionId')]/resourcegroups/[parameters('resourceGroupName')]/providers/Microsoft.Sql/servers/whoteldbserver/databases/whotel",
      "type": "mssql.azure",
      "connectionId": "ConnectionStrings:DefaultConnection",
      "secretStore": "AzureAppSettings"
    },
    "appInsights1": {
      "resourceId": "/subscriptions/[parameters('subscriptionId')]/resourcegroups/[parameters('resourceGroupName')]/providers/Microsoft.Insights/components/TheHotel",
      "type": "appInsights.azure",
      "connectionId": "APPINSIGHTS_CONNECTIONSTRING",
      "secretStore": "AzureAppSettings"
    }
  }
}